reffix/__init__.py
reffix/reffix.py
reffix/utils.py
reffix-1.2.2.dist-info/LICENSE
reffix-1.2.2.dist-info/METADATA
reffix-1.2.2.dist-info/WHEEL
reffix-1.2.2.dist-info/entry_points.txt
reffix-1.2.2.dist-info/top_level.txt
reffix-1.2.2.dist-info/RECORD
