Metadata-Version: 2.1
Name: reffix
Version: 1.2.2
Summary: A tool for fixing BibTeX reference list with DBLP API.
Author-email: Zdeněk Kasner <zdenek.kasner@gmail.com>, Ondřej Dušek <tuetschek@gmail.com>
Project-URL: Homepage, https://github.com/kasnerz/reffix
Project-URL: Bug Tracker, https://github.com/kasnerz/reffix/issues
Classifier: Programming Language :: Python :: 3
Classifier: License :: OSI Approved :: MIT License
Classifier: Operating System :: OS Independent
Requires-Python: >=3.7
License-File: LICENSE
Requires-Dist: bibtexparser (==1.4.0)
Requires-Dist: titlecase (>=2.3)
Requires-Dist: unidecode (>=1.3.4)
Requires-Dist: termcolor (>=2.2.0)
Requires-Dist: spacy (>=3.5.1)
Requires-Dist: requests
Requires-Dist: dateparser
Provides-Extra: dev
Requires-Dist: pytest ; extra == 'dev'
Requires-Dist: black ; extra == 'dev'
